{
"items" : [
  {
    "url" : "http://www.ratingruneta.ru/awards_vote/?site_id=408",
    "votes" : [5]
  },
  {
    "url" : "http://www.ratingruneta.ru/awards_vote/?site_id=40",
    "votes" : [2,3]
  },
  {
    "url" : "http://www.ratingruneta.ru/awards_vote/?site_id=215",
    "votes" : [2,3]
  },
  {
    "url" : "http://www.ratingruneta.ru/awards_vote/?site_id=157",
    "votes" : [2,3]
  },
  {
    "url" : "http://www.ratingruneta.ru/awards_vote/?site_id=385",
    "votes" : [5]
  },
  {
    "url" : "http://www.ratingruneta.ru/awards_vote/?site_id=362",
    "votes" : [2,3]
  },
  {
    "url" : "http://www.ratingruneta.ru/awards_vote/?site_id=324",
    "votes" : [2,3]
  },
  {
    "url" : "http://www.ratingruneta.ru/awards_vote/?site_id=246",
    "votes" : [2,3]
  }
]
}